hausgemachtspotipy/__init__.py
hausgemachtspotipy/hausgemachtSpotiPy.py
hausgemachtspotipy-0.1.4.dist-info/WHEEL
hausgemachtspotipy-0.1.4.dist-info/METADATA
hausgemachtspotipy-0.1.4.dist-info/RECORD
