Metadata-Version: 2.1
Name: hausgemachtspotipy
Version: 0.1.4
Summary: Access artist, album, and tracks details via Spotify Web API endpoints
License: MIT
Author: Rich Leung
Author-email: kleung.hkg@gmail.com
Requires-Python: >=3.6.1,<4.0.0
Classifier: License :: OSI Approved :: MIT License
Classifier: Programming Language :: Python :: 3
Classifier: Programming Language :: Python :: 3.7
Classifier: Programming Language :: Python :: 3.8
Classifier: Programming Language :: Python :: 3.9
Requires-Dist: DateTime (>=4.3,<5.0)
Requires-Dist: pandas (>=1.1.3,<2.0.0)
Requires-Dist: requests (>=2.24.0,<3.0.0)
